winpoll/__init__.py
winpoll/__init__.pyi
winpoll/_util/__init__.py
winpoll/_util/misc.py
winpoll/_util/misc.pyi
winpoll/_util/select_extra.py
winpoll/_util/select_extra.pyi
winpoll/_util/systeminfo.py
winpoll/_util/systeminfo.pyi
winpoll/_util/wintypes_extra.py
winpoll/_util/wintypes_extra.pyi
winpoll-0.20301.3.dist-info/licenses/LICENSE.txt
winpoll-0.20301.3.dist-info/METADATA
winpoll-0.20301.3.dist-info/WHEEL
winpoll-0.20301.3.dist-info/top_level.txt
winpoll-0.20301.3.dist-info/RECORD
