Metadata-Version: 2.4
Name: winpoll
Version: 0.20301.3
Summary: Implementation of `select.poll` on Microsoft Windows.
License-Expression: BSD-3-Clause
Keywords: poll,select.poll,WSAPoll,Windows polyfill,Windows ponyfill
Classifier: Development Status :: 3 - Alpha
Classifier: Intended Audience :: Developers
Classifier: Operating System :: Microsoft :: Windows
Classifier: Topic :: Software Development :: Libraries :: Python Modules
Classifier: Topic :: System :: Networking
Requires-Python: >=3.7
License-File: LICENSE.txt
Dynamic: license-file
